SentenceTokenizer/__init__.py
SentenceTokenizer/tokenizer.py
SentenceTokenizer/dictionaries/Titan_v2_dict_without_accentuation.json
SentenceTokenizer/dictionaries/all_portuguese_words.txt
SentenceTokenizer/dictionaries/correction_dict.json
TakeSentenceTokenizer-1.0.2.dist-info/METADATA
TakeSentenceTokenizer-1.0.2.dist-info/WHEEL
TakeSentenceTokenizer-1.0.2.dist-info/top_level.txt
TakeSentenceTokenizer-1.0.2.dist-info/RECORD
