Metadata-Version: 2.1
Name: TakeSentenceTokenizer
Version: 1.0.2
Summary: TakeSentenceTokenizer is a tool for tokenizing and pre processing messages
Home-page: UNKNOWN
Author: Karina Tiemi Kato
Author-email: karinat@take.net
License: UNKNOWN
Keywords: Tokenization
Platform: UNKNOWN
Classifier: Programming Language :: Python :: 3
Classifier: License :: OSI Approved :: MIT License
Classifier: Operating System :: OS Independent
Requires-Dist: emoji (==1.7.0)
